{
   "config_key": "rod",
   "pattern": [
      " x ",
      " x "
   ],
   "result": {
      "type": "minecraft:item",
      "item": "modernmetals:beryllium_rod"
   },
   "key": {
      "x": {
         "ore": "ingotBeryllium",
         "type": "forge:ore_dict"
      }
   },
   "type": "mmdlib:variableOutputOre",
   "conditions": [
      {
         "values": [
            {
               "optionValue": "Beryllium",
               "optionName": "material",
               "type": "mmdlib:enabled"
            },
            {
               "type": "mmdlib:enabled",
               "optionName": "thing",
               "optionValue": "Gear"
            },
            {
               "optionName": "thing",
               "optionValue": "Basics",
               "type": "mmdlib:enabled"
            }
         ],
         "type": "forge:and"
      }
   ],
   "group": "misc"
}

